{
  "format_version": "1.21.100",
  "minecraft:block": {
    "description": {
      "identifier": "zombie:infected_grass_block",
      "menu_category": {
        "category": "construction"
      }
    },
    "components": {
      "minecraft:display_name": "Infected Grass Block",
       "minecraft:destructible_by_mining": {
        "seconds_to_destroy": 1
      },
      "minecraft:destructible_by_explosion": {
        "explosion_resistance": 1200
      },
      "minecraft:map_color": "#1D1D21",
      
    "minecraft:redstone_conductivity": {"allows_wire_to_step_down": true,
    "redstone_conductor": true} 
    }
  }
}